{
  "A*": "a",
  "PW*": "b",
  "KR*": "c",
  "TK*": "d",
  "*E": "e",
  "TP*": "f",
  "TKPW*": "g",
  "H*": "h",
  "*EU": "i",
  "SKWR*": "j",
  "K*": "k",
  "HR*": "l",
  "PH*": "m",
  "TPH*": "n",
  "O*": "o",
  "P*": "p",
  "KW*": "q",
  "R*": "r",
  "S*": "s",
  "T*": "t",
  "*U": "u",
  "SR*": "v",
  "W*": "w",
  "KP*": "x",
  "KWR*": "y",
  "STPH*": "z",
  "0": "0",
  "1": "1",
  "2": "2",
  "3": "3",
  "4": "4",
  "5": "5",
  "6": "6",
  "7": "7",
  "8": "8",
  "9": "9",
  "SK*": "Escape",
  "SP*": "Space",
  "SH*": "Backspace",
  "TH*": "Return",
  "TPW*": "Tab",
  "S": "Left",
  "K": "Down",
  "W": "Up",
  "R": "Right",

  "A*": "{^}a",
  "PW*": "{^}b",
  "KR*": "{^}c",
  "TK*": "{^}d",
  "*E": "{^}e",
  "TP*": "{^}f",
  "TKPW*": "{^}g",
  "H*": "{^}h",
  "*EU": "{^}i",
  "SKWR*": "{^}j",
  "K*": "{^}k",
  "HR*": "{^}l",
  "PH*": "{^}m",
  "TPH*": "{^}n",
  "O*": "{^}o",
  "P*": "{^}p",
  "KW*": "{^}q",
  "R*": "{^}r",
  "S*": "{^}s",
  "T*": "{^}t",
  "*U": "{^}u",
  "SR*": "{^}v",
  "W*": "{^}w",
  "KP*": "{^}x",
  "KWR*": "{^}y",
  "STPH*": "{^}z",
  "0*":"{^}0",
  "1*":"{^}1",
  "2*":"{^}2",
  "3*":"{^}3",
  "4*":"{^}4",
  "5*":"{^}5",
  "*6":"{^}6",
  "*7":"{^}7",
  "*8":"{^}8",
  "*9":"{^}9",

  "A*FP": "{#Shift(a)}",
  "PW*FP": "{#Shift(b)}",
  "KR*FP": "{#Shift(c)}",
  "TK*FP": "{#Shift(d)}",
  "*EFP": "{#Shift(e)}",
  "TP*FP": "{#Shift(f)}",
  "TKPW*FP": "{#Shift(g)}",
  "H*FP": "{#Shift(h)}",
  "*EUFP": "{#Shift(i)}",
  "SKWR*FP": "{#Shift(j)}",
  "K*FP": "{#Shift(k)}",
  "HR*FP": "{#Shift(l)}",
  "PH*FP": "{#Shift(m)}",
  "TPH*FP": "{#Shift(n)}",
  "O*FP": "{#Shift(o)}",
  "P*FP": "{#Shift(p)}",
  "KW*FP": "{#Shift(q)}",
  "R*FP": "{#Shift(r)}",
  "S*FP": "{#Shift(s)}",
  "T*FP": "{#Shift(t)}",
  "*UFP": "{#Shift(u)}",
  "SR*FP": "{#Shift(v)}",
  "W*FP": "{#Shift(w)}",
  "KP*FP": "{#Shift(x)}",
  "KWR*FP": "{#Shift(y)}",
  "STPH*FP": "{#Shift(z)}",
  "0*67": "{#Shift(0)}",
  "1*67": "{#Shift(1)}",
  "2*67": "{#Shift(2)}",
  "3*67": "{#Shift(3)}",
  "4*67": "{#Shift(4)}",
  "5*67": "{#Shift(5)}",
  "23*6": "{#Shift(6)}",
  "23*7": "{#Shift(7)}",
  "23*8": "{#Shift(8)}",
  "23*9": "{#Shift(9)}",
  "SK*FP": "{#Shift(Escape)}",
  "SP*FP": "{#Shift(Space)}",
  "SH*FP": "{#Shift(Backspace)}",
  "TH*FP": "{#Shift(Return)}",
  "TPW*FP": "{#Shift(Tab)}",
  "S-FP": "{#Shift(Left)}",
  "K-FP": "{#Shift(Down)}",
  "W-FP": "{#Shift(Up)}",
  "R-FP": "{#Shift(Right)}",
  "shift+ctrl":"",
  "A*": "a",
  "PW*": "b",
  "KR*": "c",
  "TK*": "d",
  "*E": "e",
  "TP*": "f",
  "TKPW*": "g",
  "H*": "h",
  "*EU": "i",
  "SKWR*": "j",
  "K*": "k",
  "HR*": "l",
  "PH*": "m",
  "TPH*": "n",
  "O*": "o",
  "P*": "p",
  "KW*": "q",
  "R*": "r",
  "S*": "s",
  "T*": "t",
  "*U": "u",
  "SR*": "v",
  "W*": "w",
  "KP*": "x",
  "KWR*": "y",
  "STPH*": "z",
  "0": "0",
  "1": "1",
  "2": "2",
  "3": "3",
  "4": "4",
  "5": "5",
  "6": "6",
  "7": "7",
  "8": "8",
  "9": "9",
  "SK*": "Escape",
  "SP*": "Space",
  "SH*": "Backspace",
  "TH*": "Return",
  "TPW*": "Tab",
  "S": "Left",
  "K": "Down",
  "W": "Up",
  "R": "Right",
  "shift+ctrl+super":"",
  "A*": "a",
  "PW*": "b",
  "KR*": "c",
  "TK*": "d",
  "*E": "e",
  "TP*": "f",
  "TKPW*": "g",
  "H*": "h",
  "*EU": "i",
  "SKWR*": "j",
  "K*": "k",
  "HR*": "l",
  "PH*": "m",
  "TPH*": "n",
  "O*": "o",
  "P*": "p",
  "KW*": "q",
  "R*": "r",
  "S*": "s",
  "T*": "t",
  "*U": "u",
  "SR*": "v",
  "W*": "w",
  "KP*": "x",
  "KWR*": "y",
  "STPH*": "z",
  "0": "0",
  "1": "1",
  "2": "2",
  "3": "3",
  "4": "4",
  "5": "5",
  "6": "6",
  "7": "7",
  "8": "8",
  "9": "9",
  "SK*": "Escape",
  "SP*": "Space",
  "SH*": "Backspace",
  "TH*": "Return",
  "TPW*": "Tab",
  "S": "Left",
  "K": "Down",
  "W": "Up",
  "R": "Right",
  "shift+ctrl+super+alt":"",
  "A*": "a",
  "PW*": "b",
  "KR*": "c",
  "TK*": "d",
  "*E": "e",
  "TP*": "f",
  "TKPW*": "g",
  "H*": "h",
  "*EU": "i",
  "SKWR*": "j",
  "K*": "k",
  "HR*": "l",
  "PH*": "m",
  "TPH*": "n",
  "O*": "o",
  "P*": "p",
  "KW*": "q",
  "R*": "r",
  "S*": "s",
  "T*": "t",
  "*U": "u",
  "SR*": "v",
  "W*": "w",
  "KP*": "x",
  "KWR*": "y",
  "STPH*": "z",
  "0": "0",
  "1": "1",
  "2": "2",
  "3": "3",
  "4": "4",
  "5": "5",
  "6": "6",
  "7": "7",
  "8": "8",
  "9": "9",
  "SK*": "Escape",
  "SP*": "Space",
  "SH*": "Backspace",
  "TH*": "Return",
  "TPW*": "Tab",
  "S": "Left",
  "K": "Down",
  "W": "Up",
  "R": "Right",
  "shift+ctrl+alt":"",
  "A*": "a",
  "PW*": "b",
  "KR*": "c",
  "TK*": "d",
  "*E": "e",
  "TP*": "f",
  "TKPW*": "g",
  "H*": "h",
  "*EU": "i",
  "SKWR*": "j",
  "K*": "k",
  "HR*": "l",
  "PH*": "m",
  "TPH*": "n",
  "O*": "o",
  "P*": "p",
  "KW*": "q",
  "R*": "r",
  "S*": "s",
  "T*": "t",
  "*U": "u",
  "SR*": "v",
  "W*": "w",
  "KP*": "x",
  "KWR*": "y",
  "STPH*": "z",
  "0": "0",
  "1": "1",
  "2": "2",
  "3": "3",
  "4": "4",
  "5": "5",
  "6": "6",
  "7": "7",
  "8": "8",
  "9": "9",
  "SK*": "Escape",
  "SP*": "Space",
  "SH*": "Backspace",
  "TH*": "Return",
  "TPW*": "Tab",
  "S": "Left",
  "K": "Down",
  "W": "Up",
  "R": "Right",
  "shift+super":"",
  "A*": "a",
  "PW*": "b",
  "KR*": "c",
  "TK*": "d",
  "*E": "e",
  "TP*": "f",
  "TKPW*": "g",
  "H*": "h",
  "*EU": "i",
  "SKWR*": "j",
  "K*": "k",
  "HR*": "l",
  "PH*": "m",
  "TPH*": "n",
  "O*": "o",
  "P*": "p",
  "KW*": "q",
  "R*": "r",
  "S*": "s",
  "T*": "t",
  "*U": "u",
  "SR*": "v",
  "W*": "w",
  "KP*": "x",
  "KWR*": "y",
  "STPH*": "z",
  "0": "0",
  "1": "1",
  "2": "2",
  "3": "3",
  "4": "4",
  "5": "5",
  "6": "6",
  "7": "7",
  "8": "8",
  "9": "9",
  "SK*": "Escape",
  "SP*": "Space",
  "SH*": "Backspace",
  "TH*": "Return",
  "TPW*": "Tab",
  "S": "Left",
  "K": "Down",
  "W": "Up",
  "R": "Right",
  "shift+super+alt":"",
  "A*": "a",
  "PW*": "b",
  "KR*": "c",
  "TK*": "d",
  "*E": "e",
  "TP*": "f",
  "TKPW*": "g",
  "H*": "h",
  "*EU": "i",
  "SKWR*": "j",
  "K*": "k",
  "HR*": "l",
  "PH*": "m",
  "TPH*": "n",
  "O*": "o",
  "P*": "p",
  "KW*": "q",
  "R*": "r",
  "S*": "s",
  "T*": "t",
  "*U": "u",
  "SR*": "v",
  "W*": "w",
  "KP*": "x",
  "KWR*": "y",
  "STPH*": "z",
  "0": "0",
  "1": "1",
  "2": "2",
  "3": "3",
  "4": "4",
  "5": "5",
  "6": "6",
  "7": "7",
  "8": "8",
  "9": "9",
  "SK*": "Escape",
  "SP*": "Space",
  "SH*": "Backspace",
  "TH*": "Return",
  "TPW*": "Tab",
  "S": "Left",
  "K": "Down",
  "W": "Up",
  "R": "Right",
  "shift+alt":"",
  "A*": "a",
  "PW*": "b",
  "KR*": "c",
  "TK*": "d",
  "*E": "e",
  "TP*": "f",
  "TKPW*": "g",
  "H*": "h",
  "*EU": "i",
  "SKWR*": "j",
  "K*": "k",
  "HR*": "l",
  "PH*": "m",
  "TPH*": "n",
  "O*": "o",
  "P*": "p",
  "KW*": "q",
  "R*": "r",
  "S*": "s",
  "T*": "t",
  "*U": "u",
  "SR*": "v",
  "W*": "w",
  "KP*": "x",
  "KWR*": "y",
  "STPH*": "z",
  "0": "0",
  "1": "1",
  "2": "2",
  "3": "3",
  "4": "4",
  "5": "5",
  "6": "6",
  "7": "7",
  "8": "8",
  "9": "9",
  "SK*": "Escape",
  "SP*": "Space",
  "SH*": "Backspace",
  "TH*": "Return",
  "TPW*": "Tab",
  "S": "Left",
  "K": "Down",
  "W": "Up",
  "R": "Right",

  "A*PL": "{#Control(a)}",
  "PW*PL": "{#Control(b)}",
  "KR*PL": "{#Control(c)}",
  "TK*PL": "{#Control(d)}",
  "*EPL": "{#Control(e)}",
  "TP*PL": "{#Control(f)}",
  "TKPW*PL": "{#Control(g)}",
  "H*PL": "{#Control(h)}",
  "*EUPL": "{#Control(i)}",
  "SKWR*PL": "{#Control(j)}",
  "K*PL": "{#Control(k)}",
  "HR*PL": "{#Control(l)}",
  "PH*PL": "{#Control(m)}",
  "TPH*PL": "{#Control(n)}",
  "O*PL": "{#Control(o)}",
  "P*PL": "{#Control(p)}",
  "KW*PL": "{#Control(q)}",
  "R*PL": "{#Control(r)}",
  "S*PL": "{#Control(s)}",
  "T*PL": "{#Control(t)}",
  "*UPL": "{#Control(u)}",
  "SR*PL": "{#Control(v)}",
  "W*PL": "{#Control(w)}",
  "KP*PL": "{#Control(x)}",
  "KWR*PL": "{#Control(y)}",
  "STPH*PL": "{#Control(z)}",
  "0PL": "{#Control(0)}",
  "1PL": "{#Control(1)}",
  "2PL": "{#Control(2)}",
  "3PL": "{#Control(3)}",
  "4PL": "{#Control(4)}",
  "5PL": "{#Control(5)}",
  "6PL": "{#Control(6)}",
  "7PL": "{#Control(7)}",
  "8PL": "{#Control(8)}",
  "9PL": "{#Control(9)}",
  "SK*PL": "{#Control(Escape)}",
  "SP*PL": "{#Control(Space)}",
  "SH*PL": "{#Control(Backspace)}",
  "TH*PL": "{#Control(Return)}",
  "TPW*PL": "{#Control(Tab)}",
  "S-PL": "{#Control(Left)}",
  "K-PL": "{#Control(Down)}",
  "W-PL": "{#Control(Up)}",
  "R-PL": "{#Control(Right)}",
  "ctrl+super":"",
  "A*": "a",
  "PW*": "b",
  "KR*": "c",
  "TK*": "d",
  "*E": "e",
  "TP*": "f",
  "TKPW*": "g",
  "H*": "h",
  "*EU": "i",
  "SKWR*": "j",
  "K*": "k",
  "HR*": "l",
  "PH*": "m",
  "TPH*": "n",
  "O*": "o",
  "P*": "p",
  "KW*": "q",
  "R*": "r",
  "S*": "s",
  "T*": "t",
  "*U": "u",
  "SR*": "v",
  "W*": "w",
  "KP*": "x",
  "KWR*": "y",
  "STPH*": "z",
  "0": "0",
  "1": "1",
  "2": "2",
  "3": "3",
  "4": "4",
  "5": "5",
  "6": "6",
  "7": "7",
  "8": "8",
  "9": "9",
  "SK*": "Escape",
  "SP*": "Space",
  "SH*": "Backspace",
  "TH*": "Return",
  "TPW*": "Tab",
  "S": "Left",
  "K": "Down",
  "W": "Up",
  "R": "Right",
  "ctrl+super+alt":"",
  "A*": "a",
  "PW*": "b",
  "KR*": "c",
  "TK*": "d",
  "*E": "e",
  "TP*": "f",
  "TKPW*": "g",
  "H*": "h",
  "*EU": "i",
  "SKWR*": "j",
  "K*": "k",
  "HR*": "l",
  "PH*": "m",
  "TPH*": "n",
  "O*": "o",
  "P*": "p",
  "KW*": "q",
  "R*": "r",
  "S*": "s",
  "T*": "t",
  "*U": "u",
  "SR*": "v",
  "W*": "w",
  "KP*": "x",
  "KWR*": "y",
  "STPH*": "z",
  "0": "0",
  "1": "1",
  "2": "2",
  "3": "3",
  "4": "4",
  "5": "5",
  "6": "6",
  "7": "7",
  "8": "8",
  "9": "9",
  "SK*": "Escape",
  "SP*": "Space",
  "SH*": "Backspace",
  "TH*": "Return",
  "TPW*": "Tab",
  "S": "Left",
  "K": "Down",
  "W": "Up",
  "R": "Right",
  "ctrl+alt":"",
  "A*": "a",
  "PW*": "b",
  "KR*": "c",
  "TK*": "d",
  "*E": "e",
  "TP*": "f",
  "TKPW*": "g",
  "H*": "h",
  "*EU": "i",
  "SKWR*": "j",
  "K*": "k",
  "HR*": "l",
  "PH*": "m",
  "TPH*": "n",
  "O*": "o",
  "P*": "p",
  "KW*": "q",
  "R*": "r",
  "S*": "s",
  "T*": "t",
  "*U": "u",
  "SR*": "v",
  "W*": "w",
  "KP*": "x",
  "KWR*": "y",
  "STPH*": "z",
  "0": "0",
  "1": "1",
  "2": "2",
  "3": "3",
  "4": "4",
  "5": "5",
  "6": "6",
  "7": "7",
  "8": "8",
  "9": "9",
  "SK*": "Escape",
  "SP*": "Space",
  "SH*": "Backspace",
  "TH*": "Return",
  "TPW*": "Tab",
  "S": "Left",
  "K": "Down",
  "W": "Up",
  "R": "Right",

  "A*RB": "{#Super(a)}",
  "PW*RB": "{#Super(b)}",
  "KR*RB": "{#Super(c)}",
  "TK*RB": "{#Super(d)}",
  "*ERB": "{#Super(e)}",
  "TP*RB": "{#Super(f)}",
  "TKPW*RB": "{#Super(g)}",
  "H*RB": "{#Super(h)}",
  "*EURB": "{#Super(i)}",
  "SKWR*RB": "{#Super(j)}",
  "K*RB": "{#Super(k)}",
  "HR*RB": "{#Super(l)}",
  "PH*RB": "{#Super(m)}",
  "TPH*RB": "{#Super(n)}",
  "O*RB": "{#Super(o)}",
  "P*RB": "{#Super(p)}",
  "KW*RB": "{#Super(q)}",
  "R*RB": "{#Super(r)}",
  "S*RB": "{#Super(s)}",
  "T*RB": "{#Super(t)}",
  "*URB": "{#Super(u)}",
  "SR*RB": "{#Super(v)}",
  "W*RB": "{#Super(w)}",
  "KP*RB": "{#Super(x)}",
  "KWR*RB": "{#Super(y)}",
  "STPH*RB": "{#Super(z)}",
  "0-RB": "{#Super(0)}",
  "1-RB": "{#Super(1)}",
  "2-RB": "{#Super(2)}",
  "3-RB": "{#Super(3)}",
  "4-RB": "{#Super(4)}",
  "5-RB": "{#Super(5)}",
  "KW-6": "{#Super(6)}",
  "KW-7": "{#Super(7)}",
  "KW-8": "{#Super(8)}",
  "KW-9RB": "{#Super(9)}",
  "SK*RB": "{#Super(Escape)}",
  "SP*RB": "{#Super(Space)}",
  "SH*RB": "{#Super(Backspace)}",
  "TH*RB": "{#Super(Return)}",
  "TPW*RB": "{#Super(Tab)}",
  "S-RB": "{#Super(Left)}",
  "K-RB": "{#Super(Down)}",
  "W-RB": "{#Super(Up)}",
  "R-RB": "{#Super(Right)}",
  "super+alt":"",
  "A*": "a",
  "PW*": "b",
  "KR*": "c",
  "TK*": "d",
  "*E": "e",
  "TP*": "f",
  "TKPW*": "g",
  "H*": "h",
  "*EU": "i",
  "SKWR*": "j",
  "K*": "k",
  "HR*": "l",
  "PH*": "m",
  "TPH*": "n",
  "O*": "o",
  "P*": "p",
  "KW*": "q",
  "R*": "r",
  "S*": "s",
  "T*": "t",
  "*U": "u",
  "SR*": "v",
  "W*": "w",
  "KP*": "x",
  "KWR*": "y",
  "STPH*": "z",
  "0": "0",
  "1": "1",
  "2": "2",
  "3": "3",
  "4": "4",
  "5": "5",
  "6": "6",
  "7": "7",
  "8": "8",
  "9": "9",
  "SK*": "Escape",
  "SP*": "Space",
  "SH*": "Backspace",
  "TH*": "Return",
  "TPW*": "Tab",
  "S": "Left",
  "K": "Down",
  "W": "Up",
  "R": "Right",
  "alt":"",
  "A*": "a",
  "PW*": "b",
  "KR*": "c",
  "TK*": "d",
  "*E": "e",
  "TP*": "f",
  "TKPW*": "g",
  "H*": "h",
  "*EU": "i",
  "SKWR*": "j",
  "K*": "k",
  "HR*": "l",
  "PH*": "m",
  "TPH*": "n",
  "O*": "o",
  "P*": "p",
  "KW*": "q",
  "R*": "r",
  "S*": "s",
  "T*": "t",
  "*U": "u",
  "SR*": "v",
  "W*": "w",
  "KP*": "x",
  "KWR*": "y",
  "STPH*": "z",
  "0": "0",
  "1": "1",
  "2": "2",
  "3": "3",
  "4": "4",
  "5": "5",
  "6": "6",
  "7": "7",
  "8": "8",
  "9": "9",
  "SK*": "Escape",
  "SP*": "Space",
  "SH*": "Backspace",
  "TH*": "Return",
  "TPW*": "Tab",
  "S": "Left",
  "K": "Down",
  "W": "Up",
  "R": "Right",
  "": "",

  "A*": "{^}a",
  "PW*": "{^}b",
  "KR*": "{^}c",
  "TK*": "{^}d",
  "*E": "{^}e",
  "TP*": "{^}f",
  "TKPW*": "{^}g",
  "H*": "{^}h",
  "*EU": "{^}i",
  "SKWR*": "{^}j",
  "K*": "{^}k",
  "HR*": "{^}l",
  "PH*": "{^}m",
  "TPH*": "{^}n",
  "O*": "{^}o",
  "P*": "{^}p",
  "KW*": "{^}q",
  "R*": "{^}r",
  "S*": "{^}s",
  "T*": "{^}t",
  "*U": "{^}u",
  "SR*": "{^}v",
  "W*": "{^}w",
  "KP*": "{^}x",
  "KWR*": "{^}y",
  "STPH*": "{^}z",
  "0*":"{^}0",
  "1*":"{^}1",
  "2*":"{^}2",
  "3*":"{^}3",
  "4*":"{^}4",
  "5*":"{^}5",
  "*6":"{^}6",
  "*7":"{^}7",
  "*8":"{^}8",
  "*9":"{^}9",


  "": ""
}
